[
  {
    "LiveFrom": "18/03/2023",
    "CaseTypeID": "Benefit",
    "RoleName": "idam:caseworker-sscs-systemupdate",
    "Authorisation": "",
    "ReadOnly": "N",
    "AccessProfiles": "caseworker,caseworker-sscs,caseworker-sscs-systemupdate",
    "Disabled": "N"
  },
  {
    "LiveFrom": "18/03/2023",
    "CaseTypeID": "Benefit",
    "RoleName": "idam:caseworker-sscs-anonymouscitizen",
    "Authorisation": "",
    "ReadOnly": "N",
    "AccessProfiles": "caseworker,caseworker-sscs,caseworker-sscs-anonymouscitizen",
    "Disabled": "N"
  },
  {
    "LiveFrom": "18/03/2023",
    "CaseTypeID": "Benefit",
    "RoleName": "idam:caseworker-sscs-bulkscan",
    "Authorisation": "",
    "ReadOnly": "N",
    "AccessProfiles": "caseworker,caseworker-sscs,caseworker-sscs-bulkscan",
    "Disabled": "N"
  },
  {
    "LiveFrom": "18/03/2023",
    "CaseTypeID": "Benefit",
    "RoleName": "idam:citizen",
    "Authorisation": "",
    "ReadOnly": "N",
    "AccessProfiles": "citizen",
    "Disabled": "N"
  },
  {
    "LiveFrom": "18/03/2023",
    "CaseTypeID": "Benefit",
    "RoleName": "[CREATOR]",
    "Authorisation": "",
    "ReadOnly": "N",
    "AccessProfiles": "[CREATOR]",
    "Disabled": "N"
  }
]